vaex/hdf5/__init__.py
vaex/hdf5/_version.py
vaex/hdf5/dataset.py
vaex/hdf5/export.py
vaex/hdf5/utils.py
vaex/hdf5/writer.py
vaex_hdf5-0.14.1.dist-info/LICENSE.txt
vaex_hdf5-0.14.1.dist-info/METADATA
vaex_hdf5-0.14.1.dist-info/WHEEL
vaex_hdf5-0.14.1.dist-info/entry_points.txt
vaex_hdf5-0.14.1.dist-info/top_level.txt
vaex_hdf5-0.14.1.dist-info/RECORD
