Metadata-Version: 1.0
Name: vaex-hdf5
Version: 0.14.1
Summary: hdf5 file support for vaex
Home-page: https://www.github.com/maartenbreddels/vaex
Author: Maarten A. Breddels
Author-email: maartenbreddels@gmail.com
License: MIT
Platform: UNKNOWN
